audiowire/__init__.py
audiowire/__main__.py
audiowire/index.html
audiowire/settings.py
audiowire/web.py
audiowire/weui.html
audiowire/static/favicon.ico
audiowire/static/jquery.min.js
audiowire/static/pcm-player.js
audiowire/static/pcmplayer2.js
audiowire/static/reconnecting-websocket.js
audiowire/static/vue.js
audiowire/static/bootstrap-4.0.0-dist/css/bootstrap-grid.css
audiowire/static/bootstrap-4.0.0-dist/css/bootstrap-grid.css.map
audiowire/static/bootstrap-4.0.0-dist/css/bootstrap-grid.min.css
audiowire/static/bootstrap-4.0.0-dist/css/bootstrap-grid.min.css.map
audiowire/static/bootstrap-4.0.0-dist/css/bootstrap-reboot.css
audiowire/static/bootstrap-4.0.0-dist/css/bootstrap-reboot.css.map
audiowire/static/bootstrap-4.0.0-dist/css/bootstrap-reboot.min.css
audiowire/static/bootstrap-4.0.0-dist/css/bootstrap-reboot.min.css.map
audiowire/static/bootstrap-4.0.0-dist/css/bootstrap.css
audiowire/static/bootstrap-4.0.0-dist/css/bootstrap.css.map
audiowire/static/bootstrap-4.0.0-dist/css/bootstrap.min.css
audiowire/static/bootstrap-4.0.0-dist/css/bootstrap.min.css.map
audiowire/static/bootstrap-4.0.0-dist/js/bootstrap.bundle.js
audiowire/static/bootstrap-4.0.0-dist/js/bootstrap.bundle.js.map
audiowire/static/bootstrap-4.0.0-dist/js/bootstrap.bundle.min.js
audiowire/static/bootstrap-4.0.0-dist/js/bootstrap.bundle.min.js.map
audiowire/static/bootstrap-4.0.0-dist/js/bootstrap.js
audiowire/static/bootstrap-4.0.0-dist/js/bootstrap.js.map
audiowire/static/bootstrap-4.0.0-dist/js/bootstrap.min.js
audiowire/static/bootstrap-4.0.0-dist/js/bootstrap.min.js.map
audiowire-0.1.1.dev1.dist-info/AUTHORS
audiowire-0.1.1.dev1.dist-info/LICENSE
audiowire-0.1.1.dev1.dist-info/METADATA
audiowire-0.1.1.dev1.dist-info/WHEEL
audiowire-0.1.1.dev1.dist-info/entry_points.txt
audiowire-0.1.1.dev1.dist-info/pbr.json
audiowire-0.1.1.dev1.dist-info/top_level.txt
audiowire-0.1.1.dev1.dist-info/RECORD
